chrome_trex_gym/DinoGame.py
chrome_trex_gym/__init__.py
chrome_trex_gym/envs/ChromeTrexEnv.py
chrome_trex_gym/envs/__init__.py
chrome_trex_gym/sprites/cacti-big.png
chrome_trex_gym/sprites/cacti-small.png
chrome_trex_gym/sprites/cloud.png
chrome_trex_gym/sprites/dino.png
chrome_trex_gym/sprites/dino_ducking.png
chrome_trex_gym/sprites/ground.png
chrome_trex_gym/sprites/numbers.png
chrome_trex_gym/sprites/offline-sprite-2x-black.png
chrome_trex_gym/sprites/ptera.png
chrome_trex_gym-0.0.4.dist-info/LICENSE
chrome_trex_gym-0.0.4.dist-info/METADATA
chrome_trex_gym-0.0.4.dist-info/WHEEL
chrome_trex_gym-0.0.4.dist-info/top_level.txt
chrome_trex_gym-0.0.4.dist-info/RECORD
