Metadata-Version: 2.1
Name: chrome-trex-gym
Version: 0.0.4
Summary: A gym environement for the chrome trex game
Home-page: https://github.com/BadrYoubiIdrissi/chrome-trex-gym.git
Author: Badr Youbi Idrissi
Author-email: badryoubiidrissi@gmail.com
License: UNKNOWN
Platform: UNKNOWN
Classifier: Programming Language :: Python :: 3
Classifier: License :: OSI Approved :: MIT License
Classifier: Operating System :: OS Independent
